MANIFEST.in
README.md
setup.py
loterie/__init__.py
loterie/kostka.py
loterie/loterie.py
python_technology_CZ10_loterie.egg-info/PKG-INFO
python_technology_CZ10_loterie.egg-info/SOURCES.txt
python_technology_CZ10_loterie.egg-info/dependency_links.txt
python_technology_CZ10_loterie.egg-info/requires.txt
python_technology_CZ10_loterie.egg-info/top_level.txt